README.txt
setup.py
src/gum/SSHA.py
src/gum/__init__.py
src/gum/cookiecredentials.py
src/gum/extensions.py
src/gum/group.py
src/gum/interfaces.py
src/gum/layout.py
src/gum/ldapapp.py
src/gum/login.py
src/gum/migrations.py
src/gum/organization.py
src/gum/smart.py
src/gum/tests.py
src/gum/transcript.py
src/gum/user.py
src/gum/vocabularies.py
src/gum/widgets.py
src/gum.egg-info/PKG-INFO
src/gum.egg-info/SOURCES.txt
src/gum.egg-info/dependency_links.txt
src/gum.egg-info/entry_points.txt
src/gum.egg-info/not-zip-safe
src/gum.egg-info/requires.txt
src/gum.egg-info/top_level.txt
src/gum/ftests/__init__.py
src/gum/ftests/xmlrpc_helper.py