Metadata-Version: 1.0
Name: gum
Version: 0.8.1
Summary: GUM is a web application for managing users and groups stored in an LDAP server.
Home-page: http://www.bcgsc.ca/platform/bioinfo/software/gum
Author: Kevin Teague
Author-email: Kevin Teague <kteague@bcgsc.ca>
License: ZPL
Platform: UNKNOWN
Classifier: Programming Language :: Python
Classifier: Development Status :: 4 - Beta
Classifier: Framework :: Zope3
Classifier: Intended Audience :: System Administrators
Classifier: License :: OSI Approved :: Zope Public License
Classifier: Topic :: System :: Systems Administration :: Authentication/Directory :: LDAP
